idemenv/conf.py
idemenv/scripts.py
idemenv/version.py
idemenv/idemenv/cli.py
idemenv/idemenv/init.py
idemenv/idemenv/ops.py
idemenv-0.2.0.dist-info/LICENSE
idemenv-0.2.0.dist-info/METADATA
idemenv-0.2.0.dist-info/WHEEL
idemenv-0.2.0.dist-info/entry_points.txt
idemenv-0.2.0.dist-info/top_level.txt
idemenv-0.2.0.dist-info/RECORD
