Metadata-Version: 2.1
Name: idemenv
Version: 0.2.0
Summary: Idem binary installation and management tool
Home-page: https://github.com/eitrtechnologies/idemenv
Author: EITR Technologies, LLC
Author-email: devops@eitr.tech
License: UNKNOWN
Platform: UNKNOWN
Classifier: Environment :: Console
Classifier: Intended Audience :: Developers
Classifier: Intended Audience :: Information Technology
Classifier: Intended Audience :: System Administrators
Classifier: Operating System :: OS Independent
Classifier: Programming Language :: Python
Classifier: Programming Language :: Python :: 3.7
Classifier: Programming Language :: Python :: 3.8
Classifier: Programming Language :: Python :: 3.9
Classifier: Programming Language :: Python :: 3.10
Classifier: Development Status :: 5 - Production/Stable
Requires-Python: >=3.7
License-File: LICENSE
Requires-Dist: pop (>=17.0)
Requires-Dist: pop-aiohttp
Requires-Dist: bs4
